titi/__about__.py
titi/__init__.py
titi/code.py
titi-0.0.1.dist-info/METADATA
titi-0.0.1.dist-info/WHEEL
titi-0.0.1.dist-info/licenses/LICENSE.txt
titi-0.0.1.dist-info/RECORD
